.gitignore
AUTHORS.txt
COPYING.txt
README.txt
setup.py
setuptools_git.py
setuptools_git.egg-info/PKG-INFO
setuptools_git.egg-info/SOURCES.txt
setuptools_git.egg-info/dependency_links.txt
setuptools_git.egg-info/entry_points.txt
setuptools_git.egg-info/top_level.txt
