Metadata-Version: 1.0
Name: setuptools_git
Version: 0.3.4
Summary: Setuptools revision control system plugin for Git
Home-page: UNKNOWN
Author: Yannick Gingras
Author-email: ygingras@ygingras.net
License: Public Domain
Platform: UNKNOWN
Classifier: Topic :: Software Development :: Version Control
Classifier: Development Status :: 4 - Beta
Classifier: Intended Audience :: Developers
Classifier: License :: Public Domain
Classifier: Programming Language :: Python
